commons/__init__.py
commons/say_hello.py
commons/config/__init__.py
commons/config/config.py
commons/data/__init__.py
commons/data/handle_common.py
commons/file/__init__.py
commons/file/handle_system.py
commons/file/readFile.py
commons/plugin/__init__.py
smart-auto-test/__init__.py
smart-auto-test/say_hello.py
smart_auto_test-0.0.6.dist-info/LICENSE
smart_auto_test-0.0.6.dist-info/METADATA
smart_auto_test-0.0.6.dist-info/WHEEL
smart_auto_test-0.0.6.dist-info/top_level.txt
smart_auto_test-0.0.6.dist-info/RECORD
